MANIFEST.in
README.md
setup.py
mobs/__init__.py
mobs.egg-info/PKG-INFO
mobs.egg-info/SOURCES.txt
mobs.egg-info/dependency_links.txt
mobs.egg-info/requires.txt
mobs.egg-info/top_level.txt
mobs/config/pattern.yaml
mobs/utils/__init__.py
mobs/utils/diffUtils.py
mobs/utils/exceptions.py
mobs/utils/extractUtils.py
mobs/utils/loadUtils.py
mobs/utils/takes.py