Metadata-Version: 1.1
Name: mobs
Version: 0.1.2
Summary: Mobs tool
Home-page: UNKNOWN
Author: YJ-L
Author-email: lewyuejian@163.com
License: UNKNOWN
Platform: UNKNOWN
Classifier: Programming Language :: Python :: 3.6
Classifier: Programming Language :: Python :: 3.7
Classifier: Programming Language :: Python :: 3.8
Classifier: License :: OSI Approved :: MIT License
Classifier: Operating System :: OS Independent
